{
    "id": "3a38d628-a22b-49af-bd96-4c0f7a282e4c",
    "artist": "Kendrick Lamar Featuring AzChike",
    "song": "Peekaboo",
    "youtube_url": "https://www.youtube.com/watch?v=cbHkzwa0QmM",
    "uploader": "Kendrick Lamar",
    "duration": 156,
    "views": 27527394,
    "like_count": 393636,
    "release_date": "",
    "thumbnail": "https://i.ytimg.com/vi/cbHkzwa0QmM/maxresdefault.jpg",
    "tags": [],
    "description": "Kendrick Lamar \u201cGNX\u201d is available now: https://my-gnx.com/\n\nhttps://www.myGNX.com\nhttps://www.instagram.com/kendricklamar\nhttps://twitter.com/kendricklamar\nhttps://www.facebook.com/kendricklamar\n\n#KendrickLamar #GNX",
    "last_updated": 1742628352
}